marshmallow_generic/__init__.py
marshmallow_generic/_util.py
marshmallow_generic/decorators.py
marshmallow_generic/py.typed
marshmallow_generic/schema.py
marshmallow_generic-1.0.1.dist-info/LICENSE
marshmallow_generic-1.0.1.dist-info/METADATA
marshmallow_generic-1.0.1.dist-info/WHEEL
marshmallow_generic-1.0.1.dist-info/top_level.txt
marshmallow_generic-1.0.1.dist-info/RECORD
