Metadata-Version: 2.1
Name: marshmallow-generic
Version: 1.0.1
Summary: Generic schema with full typing support and minimal boilerplate
Author-email: Daniil Fajnberg <mail@daniil.fajnberg.de>
Maintainer-email: Daniil Fajnberg <mail@daniil.fajnberg.de>
License: Apache Software License Version 2.0
Project-URL: Repository, https://github.com/daniil-berg/marshmallow-generic
Project-URL: Issue Tracker, https://github.com/daniil-berg/marshmallow-generic/issues
Project-URL: Documentation, http://daniil-berg.github.io/marshmallow-generic
Classifier: Development Status :: 5 - Production/Stable
Classifier: Programming Language :: Python :: 3 :: Only
Classifier: Programming Language :: Python :: 3.9
Classifier: Programming Language :: Python :: 3.10
Classifier: Programming Language :: Python :: 3.11
Classifier: Operating System :: OS Independent
Classifier: License :: OSI Approved :: Apache Software License
Classifier: Intended Audience :: Developers
Classifier: Typing :: Typed
Requires-Python: <4.0,>=3.9
License-File: LICENSE
Requires-Dist: marshmallow (>=3.12.0)
Provides-Extra: dev
Requires-Dist: black (==23.3.0) ; extra == 'dev'
Requires-Dist: build (==0.10.0) ; extra == 'dev'
Requires-Dist: coverage[toml] (==7.2.3) ; extra == 'dev'
Requires-Dist: isort (==5.12.0) ; extra == 'dev'
Requires-Dist: mkdocs-material (==9.1.6) ; extra == 'dev'
Requires-Dist: mkdocstrings[python] (==0.21.2) ; extra == 'dev'
Requires-Dist: mypy (==1.2.0) ; extra == 'dev'
Requires-Dist: ruff (==0.0.262) ; extra == 'dev'
